voibot/__init__.py
voibot/chatbot.py
voibot/config.py
voibot/utils.py
voibot-0.1.11.dist-info/LICENSE
voibot-0.1.11.dist-info/METADATA
voibot-0.1.11.dist-info/WHEEL
voibot-0.1.11.dist-info/top_level.txt
voibot-0.1.11.dist-info/RECORD
